kohonen/__init__.py
kohonen/kohonen.py
kohonen-1.1.2.dist-info/DESCRIPTION.rst
kohonen-1.1.2.dist-info/METADATA
kohonen-1.1.2.dist-info/metadata.json
kohonen-1.1.2.dist-info/RECORD
kohonen-1.1.2.dist-info/top_level.txt
kohonen-1.1.2.dist-info/WHEEL
