Metadata-Version: 1.1
Name: kohonen
Version: 1.1.2
Summary: A library of vector quantizers
Home-page: http://github.com/lmjohns3/py-kohonen
Author: Leif Johnson
Author-email: leif@leifjohnson.net
License: MIT
Keywords: kohonen self-organizing-map neural-gas growing-neural-gas vector-quantization machine-learning
Platform: UNKNOWN
Classifier: Development Status :: 5 - Production/Stable
Classifier: Intended Audience :: Science/Research
Classifier: License :: OSI Approved :: MIT License
Classifier: Operating System :: OS Independent
Classifier: Topic :: Scientific/Engineering :: Artificial Intelligence
